textart.py
textart-1.0.0b0.dist-info/DESCRIPTION.rst
textart-1.0.0b0.dist-info/METADATA
textart-1.0.0b0.dist-info/RECORD
textart-1.0.0b0.dist-info/WHEEL
textart-1.0.0b0.dist-info/metadata.json
textart-1.0.0b0.dist-info/top_level.txt
