Metadata-Version: 2.0
Name: textart
Version: 1.0.0b0
Summary: A package for drawing art-text with similar functionality to pygame
Home-page: https://github.com/billy-yoyo/textart/
Author: Billyoyo
Author-email: billyoyo@hotmail.co.uk
License: MIT
